squadron/__init__.py
squadron/agents.yaml
squadron/brain.py
squadron/cli.py
squadron/listener.py
squadron/overseer.py
squadron/server.py
squadron/evolution/__init__.py
squadron/evolution/gardener.py
squadron/evolution/improver.py
squadron/evolution/skill_registry.py
squadron/evolution/watcher.py
squadron/knowledge/CODEBASE_MAP.md
squadron/knowledge/ROLES.md
squadron/knowledge/TEAM.md
squadron/knowledge/WORKFLOW.md
squadron/knowledge/__init__.py
squadron/knowledge/reader.py
squadron/memory/__init__.py
squadron/memory/hippocampus.py
squadron/planner/__init__.py
squadron/planner/architect.py
squadron/services/__init__.py
squadron/services/comment_watcher.py
squadron/services/event_bus.py
squadron/services/model_factory.py
squadron/services/strategist.py
squadron/services/tag_parser.py
squadron/services/wake_protocol.py
squadron/services/llm/__init__.py
squadron/services/llm/deepseek.py
squadron/services/llm/gemini.py
squadron/services/llm/openai.py
squadron/skills/COLLABORATION.md
squadron/skills/__init__.py
squadron/skills/workspace_tool.py
squadron/skills/discord_bridge/SKILL.md
squadron/skills/discord_bridge/__init__.py
squadron/skills/discord_bridge/bot.py
squadron/skills/discord_bridge/tool.py
squadron/skills/dynamic/__init__.py
squadron/skills/fs_tool/__init__.py
squadron/skills/fs_tool/tool.py
squadron/skills/github_bridge/SKILL.md
squadron/skills/github_bridge/__init__.py
squadron/skills/github_bridge/tool.py
squadron/skills/jira_bridge/SKILL.md
squadron/skills/jira_bridge/__init__.py
squadron/skills/jira_bridge/tool.py
squadron/skills/librarian/SKILL.md
squadron/skills/librarian/__init__.py
squadron/skills/librarian/tool.py
squadron/skills/linear_bridge/SKILL.md
squadron/skills/linear_bridge/__init__.py
squadron/skills/linear_bridge/tool.py
squadron/skills/memory/__init__.py
squadron/skills/memory/tool.py
squadron/skills/planner/SKILL.md
squadron/skills/planner/__init__.py
squadron/skills/planner/tool.py
squadron/skills/shell_tool/__init__.py
squadron_agents-0.5.1.dist-info/licenses/LICENSE
squadron_agents-0.5.1.dist-info/METADATA
squadron_agents-0.5.1.dist-info/WHEEL
squadron_agents-0.5.1.dist-info/entry_points.txt
squadron_agents-0.5.1.dist-info/top_level.txt
squadron_agents-0.5.1.dist-info/RECORD
