Metadata-Version: 2.4
Name: squadron-agents
Version: 0.5.1
Summary: The Operating System for Autonomous Software Teams
Home-page: https://github.com/MikeeBuilds/squadron
Author: MikeeBuilds
Author-email: mludlow000@icloud.com
Classifier: Development Status :: 4 - Beta
Classifier: Intended Audience :: Developers
Classifier: Topic :: Software Development :: Build Tools
Classifier: License :: OSI Approved :: GNU Affero General Public License v3
Classifier: Programming Language :: Python :: 3
Classifier: Programming Language :: Python :: 3.10
Classifier: Programming Language :: Python :: 3.11
Classifier: Programming Language :: Python :: 3.12
Requires-Python: >=3.10
License-File: LICENSE
Requires-Dist: python-dotenv
Requires-Dist: rich
Requires-Dist: requests
Requires-Dist: PyYAML
Requires-Dist: google-generativeai
Requires-Dist: fastapi
Requires-Dist: uvicorn[standard]
Requires-Dist: jira
Requires-Dist: slack_sdk
Requires-Dist: slack_bolt
Requires-Dist: discord.py
Requires-Dist: PyGithub
Requires-Dist: paramiko
Requires-Dist: playwright
Requires-Dist: chromadb
Requires-Dist: mcp
Provides-Extra: dev
Requires-Dist: pytest; extra == "dev"
Requires-Dist: black; extra == "dev"
Requires-Dist: flake8; extra == "dev"
Dynamic: author
Dynamic: author-email
Dynamic: classifier
Dynamic: description
Dynamic: description-content-type
Dynamic: home-page
Dynamic: license-file
Dynamic: provides-extra
Dynamic: requires-dist
Dynamic: requires-python
Dynamic: summary
